handwritting_generator/__init__.py
handwritting_generator/font.py
handwritting_generator/generator.py
handwritting_generator/test.py
handwritting_generator/content/Jayadhira.ttf
handwritting_generator/content/Lemon Tuesday.otf
handwritting_generator/content/amandasignature.ttf
handwritting_generator/content/back.png
handwritting_generator/content/back1.png
handwritting_generator/content/back_wide.png
handwritting_generator/content/bimbo.regular.ttf
handwritting_generator/content/dark2.png
handwritting_generator/content/dark2_wide.png
handwritting_generator/content/dark_wide.png
handwritting_generator/content/form1.png
handwritting_generator/content/form2.png
handwritting_generator/content/form2_wide.png
handwritting_generator/content/form3.png
handwritting_generator/content/form3_wide.png
handwritting_generator/content/grid_wide.png
handwritting_generator/content/lines.png
handwritting_generator/content/lines_wide.png
handwritting_generator/content/mathilde.regular.otf
handwritting_generator/content/ofont.ru_BetinaScriptCTT.ttf
handwritting_generator/content/ofont.ru_Denistina.ttf
handwritting_generator/content/ofont.ru_Eskal.ttf
handwritting_generator/content/ofont.ru_Marutya.ttf
handwritting_generator/content/ofont.ru_Rozovii Chulok.ttf
handwritting_generator/content/ofont.ru_Shlapak Script.otf
handwritting_generator/content/passport.png
handwritting_generator/content/passport1.png
handwritting_generator/content/passport15.png
handwritting_generator/content/passport16.png
handwritting_generator/content/passport2.png
handwritting_generator/content/passport3.png
handwritting_generator/content/passport4.png
handwritting_generator/content/passport4_wide.png
handwritting_generator/content/passport5.png
handwritting_generator/content/passport5_wide.png
handwritting_generator/content/passport6.png
handwritting_generator/content/passport6_wide.png
handwritting_generator/content/passport7.png
handwritting_generator/content/passport7_wide_exp.png
handwritting_generator-1.9.3.dist-info/METADATA
handwritting_generator-1.9.3.dist-info/WHEEL
handwritting_generator-1.9.3.dist-info/top_level.txt
handwritting_generator-1.9.3.dist-info/RECORD
